sopel_help/__init__.py
sopel_help/config.py
sopel_help/managers.py
sopel_help/mixins.py
sopel_help/plugin.py
sopel_help/providers.py
sopel_help-0.5.2.dist-info/LICENSE.txt
sopel_help-0.5.2.dist-info/METADATA
sopel_help-0.5.2.dist-info/WHEEL
sopel_help-0.5.2.dist-info/entry_points.txt
sopel_help-0.5.2.dist-info/top_level.txt
sopel_help-0.5.2.dist-info/RECORD
