Metadata-Version: 2.1
Name: sopel-help
Version: 0.5.2
Summary: Help plugin for Sopel
Author-email: dgw <dgw@technobabbl.es>, Florian Strzelecki <florian.strzelecki@gmail.com>
Maintainer-email: dgw <dgw@technobabbl.es>, Florian Strzelecki <florian.strzelecki@gmail.com>
License: EFL-2.0
Project-URL: Bug Tracker, https://github.com/sopel-irc/sopel-help/issues
Project-URL: Source, https://github.com/sopel-irc/sopel-help
Keywords: sopel,irc,help,doc,plugin
Platform: Linux x86, x86-64
Classifier: Development Status :: 4 - Beta
Classifier: Intended Audience :: Developers
Classifier: Intended Audience :: System Administrators
Classifier: License :: Eiffel Forum License (EFL)
Classifier: License :: OSI Approved :: Eiffel Forum License
Classifier: Operating System :: POSIX :: Linux
Classifier: Programming Language :: Python :: 3.8
Classifier: Programming Language :: Python :: 3.9
Classifier: Programming Language :: Python :: 3.10
Classifier: Programming Language :: Python :: 3.11
Classifier: Programming Language :: Python :: 3.12
Classifier: Topic :: Communications :: Chat :: Internet Relay Chat
Requires-Python: >=3.8
License-File: LICENSE.txt
Requires-Dist: sopel>=7.1
Requires-Dist: requests
Requires-Dist: importlib-metadata>=3.6
